dfa_gym/__init__.py
dfa_gym/dfa_env.py
dfa_gym/dfa_wrapper.py
dfa_gym-0.1.0.dist-info/METADATA
dfa_gym-0.1.0.dist-info/WHEEL
dfa_gym-0.1.0.dist-info/licenses/LICENSE
dfa_gym-0.1.0.dist-info/RECORD
